{
	"location_list": [
		{
			"location": "Sea World",
			"Note": "Remember to bring Alex"			
		},
		
		{
			"location": "Texas Roadhouse",
			"Note": "None"			
		},		

		{
			"location": "32.884857 -117.222422",
			"Note": "Amazing building, bring Jonna here."			
		},	
		{
			"location": "142 Rocky Point Rd...",
			"Note": "Here is a Seafood market"			
		},		

		{
			"location": "114, Del cambre...",
			"Note": "A super cheap gas station"			
		},
		{
			"location": "8820 Loma Linda Dr.",
			"Note": "none"			
		},
		{
			"location": "42.884857 -127.222422",
			"Note": "Misha gonna like it."			
		},	
		{
			"location": "32.879018, -117.235945",
			"Note": ""			
		}
	]
}